seven_wxapp/__init__.py
seven_wxapp/handlers/__init__.py
seven_wxapp/handlers/base/__init__.py
seven_wxapp/handlers/base/behavior_base.py
seven_wxapp/handlers/base/client_base.py
seven_wxapp/handlers/base/seven_helper.py
seven_wxapp/handlers/base/wechat_base.py
seven_wxapp/handlers/base/wechatpay_base.py
seven_wxapp/models/__init__.py
seven_wxapp/models/seven_model.py
seven_wxapp/models/db_models/__init__.py
seven_wxapp/models/db_models/behavior/__init__.py
seven_wxapp/models/db_models/behavior/behavior_log_model.py
seven_wxapp/models/db_models/behavior/behavior_orm_model.py
seven_wxapp/models/db_models/behavior/behavior_report_model.py
seven_wxapp-1.0.14.7.dist-info/LICENSE
seven_wxapp-1.0.14.7.dist-info/METADATA
seven_wxapp-1.0.14.7.dist-info/WHEEL
seven_wxapp-1.0.14.7.dist-info/top_level.txt
seven_wxapp-1.0.14.7.dist-info/RECORD
