Metadata-Version: 2.1
Name: seven-wxapp
Version: 1.0.14.7
Summary: seven wxapp
Home-page: http://gitlab.tdtech.gao7.com/wxapp/seven_wxapp.git
Author: seven
Author-email: tech@gao7.com
License: MIT
Platform: UNKNOWN
Classifier: Topic :: Software Development :: Libraries :: Python Modules
Classifier: Programming Language :: Python
Classifier: Programming Language :: Python :: 3.4
Classifier: Programming Language :: Python :: 3.5
Classifier: Programming Language :: Python :: 3.5
Classifier: Programming Language :: Python :: 3.6
Classifier: Programming Language :: Python :: 3.7
Classifier: Programming Language :: Python :: 3.8
Classifier: Programming Language :: Python :: 3.9
Requires-Python: ~=3.4
License-File: LICENSE
Requires-Dist: seven-framework (>=1.0.121)
